hopara/__init__.py
hopara/config.py
hopara/filter.py
hopara/from_pandas.py
hopara/hopara.py
hopara/request.py
hopara/table.py
hopara/type.py
hopara/view.py
hopara-1.23.0.dist-info/METADATA
hopara-1.23.0.dist-info/WHEEL
hopara-1.23.0.dist-info/top_level.txt
hopara-1.23.0.dist-info/RECORD
