Metadata-Version: 2.4
Name: hopara
Version: 1.23.0
Summary: Hopara Python Library
Author: Hopara Inc
Requires-Dist: pandas
Requires-Dist: requests
Requires-Dist: toml
Dynamic: author
Dynamic: description
Dynamic: description-content-type
Dynamic: requires-dist
Dynamic: summary
